[{"model": "auth.group", "pk": 11, "fields": {"name": "Medical Doctors", "permissions": [163, 164, 165, 166, 167, 168, 169, 170, 33, 34, 35, 36, 37, 38, 39, 40, 1, 2, 3, 4, 9, 10, 11, 12, 5, 6, 7, 8, 13, 14, 15, 16, 99, 100, 101, 102, 187, 188, 189, 190, 183, 184, 185, 186, 191, 192, 193, 194, 151, 152, 153, 154, 143, 144, 145, 146, 147, 148, 149, 150, 83, 84, 85, 86, 87, 88, 89, 90, 65, 66, 67, 70, 69, 68, 91, 92, 93, 94, 95, 96, 97, 98, 71, 72, 73, 74, 75, 76, 77, 78, 79, 80, 81, 82, 135, 136, 137, 138, 119, 120, 121, 122, 107, 108, 109, 110, 111, 112, 113, 114, 123, 124, 125, 126, 115, 116, 117, 118, 155, 156, 157, 158, 159, 160, 161, 162, 44, 49, 50, 51, 52, 61, 62, 63, 64, 53, 54, 55, 56, 57, 58, 59, 60, 45, 46, 47, 48, 131, 132, 133, 134, 127, 128, 129, 130, 139, 140, 141, 142, 17, 18, 19, 20, 103, 104, 105, 106, 21, 22, 23, 24, 171, 172, 173, 174, 175, 176, 177, 178, 179, 180, 181, 182, 25, 26, 27, 28, 29, 30, 31, 32]}}, {"model": "auth.group", "pk": 12, "fields": {"name": "Residents", "permissions": [65, 66, 67, 70, 69, 68, 44, 49, 50, 51, 52, 57, 58, 59, 60]}}, {"model": "auth.group", "pk": 13, "fields": {"name": "Nurses", "permissions": [65, 66, 67, 70, 69, 68, 44, 49, 50, 52, 57, 58, 60]}}, {"model": "auth.group", "pk": 14, "fields": {"name": "Physiotherapists", "permissions": [65, 66, 67, 70, 69, 68, 44, 49, 50, 51, 52, 57, 58, 59, 60]}}, {"model": "auth.group", "pk": 15, "fields": {"name": "Students", "permissions": [68, 44, 52, 60]}}, {"model": "auth.permission", "pk": 1, "fields": {"name": "Can add log entry", "content_type": 1, "codename": "add_logentry"}}, {"model": "auth.permission", "pk": 2, "fields": {"name": "Can change log entry", "content_type": 1, "codename": "change_logentry"}}, {"model": "auth.permission", "pk": 3, "fields": {"name": "Can delete log entry", "content_type": 1, "codename": "delete_logentry"}}, {"model": "auth.permission", "pk": 4, "fields": {"name": "Can view log entry", "content_type": 1, "codename": "view_logentry"}}, {"model": "auth.permission", "pk": 5, "fields": {"name": "Can add permission", "content_type": 2, "codename": "add_permission"}}, {"model": "auth.permission", "pk": 6, "fields": {"name": "Can change permission", "content_type": 2, "codename": "change_permission"}}, {"model": "auth.permission", "pk": 7, "fields": {"name": "Can delete permission", "content_type": 2, "codename": "delete_permission"}}, {"model": "auth.permission", "pk": 8, "fields": {"name": "Can view permission", "content_type": 2, "codename": "view_permission"}}, {"model": "auth.permission", "pk": 9, "fields": {"name": "Can add group", "content_type": 3, "codename": "add_group"}}, {"model": "auth.permission", "pk": 10, "fields": {"name": "Can change group", "content_type": 3, "codename": "change_group"}}, {"model": "auth.permission", "pk": 11, "fields": {"name": "Can delete group", "content_type": 3, "codename": "delete_group"}}, {"model": "auth.permission", "pk": 12, "fields": {"name": "Can view group", "content_type": 3, "codename": "view_group"}}, {"model": "auth.permission", "pk": 13, "fields": {"name": "Can add content type", "content_type": 4, "codename": "add_contenttype"}}, {"model": "auth.permission", "pk": 14, "fields": {"name": "Can change content type", "content_type": 4, "codename": "change_contenttype"}}, {"model": "auth.permission", "pk": 15, "fields": {"name": "Can delete content type", "content_type": 4, "codename": "delete_contenttype"}}, {"model": "auth.permission", "pk": 16, "fields": {"name": "Can view content type", "content_type": 4, "codename": "view_contenttype"}}, {"model": "auth.permission", "pk": 17, "fields": {"name": "Can add session", "content_type": 5, "codename": "add_session"}}, {"model": "auth.permission", "pk": 18, "fields": {"name": "Can change session", "content_type": 5, "codename": "change_session"}}, {"model": "auth.permission", "pk": 19, "fields": {"name": "Can delete session", "content_type": 5, "codename": "delete_session"}}, {"model": "auth.permission", "pk": 20, "fields": {"name": "Can view session", "content_type": 5, "codename": "view_session"}}, {"model": "auth.permission", "pk": 21, "fields": {"name": "Can add site", "content_type": 6, "codename": "add_site"}}, {"model": "auth.permission", "pk": 22, "fields": {"name": "Can change site", "content_type": 6, "codename": "change_site"}}, {"model": "auth.permission", "pk": 23, "fields": {"name": "Can delete site", "content_type": 6, "codename": "delete_site"}}, {"model": "auth.permission", "pk": 24, "fields": {"name": "Can view site", "content_type": 6, "codename": "view_site"}}, {"model": "auth.permission", "pk": 25, "fields": {"name": "Can add tag", "content_type": 7, "codename": "add_tag"}}, {"model": "auth.permission", "pk": 26, "fields": {"name": "Can change tag", "content_type": 7, "codename": "change_tag"}}, {"model": "auth.permission", "pk": 27, "fields": {"name": "Can delete tag", "content_type": 7, "codename": "delete_tag"}}, {"model": "auth.permission", "pk": 28, "fields": {"name": "Can view tag", "content_type": 7, "codename": "view_tag"}}, {"model": "auth.permission", "pk": 29, "fields": {"name": "Can add tagged item", "content_type": 8, "codename": "add_taggeditem"}}, {"model": "auth.permission", "pk": 30, "fields": {"name": "Can change tagged item", "content_type": 8, "codename": "change_taggeditem"}}, {"model": "auth.permission", "pk": 31, "fields": {"name": "Can delete tagged item", "content_type": 8, "codename": "delete_taggeditem"}}, {"model": "auth.permission", "pk": 32, "fields": {"name": "Can view tagged item", "content_type": 8, "codename": "view_taggeditem"}}, {"model": "auth.permission", "pk": 33, "fields": {"name": "Can add user", "content_type": 9, "codename": "add_eqmdcustomuser"}}, {"model": "auth.permission", "pk": 34, "fields": {"name": "Can change user", "content_type": 9, "codename": "change_eqmdcustomuser"}}, {"model": "auth.permission", "pk": 35, "fields": {"name": "Can delete user", "content_type": 9, "codename": "delete_eqmdcustomuser"}}, {"model": "auth.permission", "pk": 36, "fields": {"name": "Can view user", "content_type": 9, "codename": "view_eqmdcustomuser"}}, {"model": "auth.permission", "pk": 37, "fields": {"name": "Can add user profile", "content_type": 10, "codename": "add_userprofile"}}, {"model": "auth.permission", "pk": 38, "fields": {"name": "Can change user profile", "content_type": 10, "codename": "change_userprofile"}}, {"model": "auth.permission", "pk": 39, "fields": {"name": "Can delete user profile", "content_type": 10, "codename": "delete_userprofile"}}, {"model": "auth.permission", "pk": 40, "fields": {"name": "Can view user profile", "content_type": 10, "codename": "view_userprofile"}}, {"model": "auth.permission", "pk": 41, "fields": {"name": "Can add Tag Permitida", "content_type": 11, "codename": "add_allowedtag"}}, {"model": "auth.permission", "pk": 42, "fields": {"name": "Can change Tag Permitida", "content_type": 11, "codename": "change_allowedtag"}}, {"model": "auth.permission", "pk": 43, "fields": {"name": "Can delete Tag Permitida", "content_type": 11, "codename": "delete_allowedtag"}}, {"model": "auth.permission", "pk": 44, "fields": {"name": "Can view Tag Permitida", "content_type": 11, "codename": "view_allowedtag"}}, {"model": "auth.permission", "pk": 45, "fields": {"name": "Can add Ala", "content_type": 12, "codename": "add_ward"}}, {"model": "auth.permission", "pk": 46, "fields": {"name": "Can change Ala", "content_type": 12, "codename": "change_ward"}}, {"model": "auth.permission", "pk": 47, "fields": {"name": "Can delete Ala", "content_type": 12, "codename": "delete_ward"}}, {"model": "auth.permission", "pk": 48, "fields": {"name": "Can view Ala", "content_type": 12, "codename": "view_ward"}}, {"model": "auth.permission", "pk": 49, "fields": {"name": "Can add Paciente", "content_type": 13, "codename": "add_patient"}}, {"model": "auth.permission", "pk": 50, "fields": {"name": "Can change Paciente", "content_type": 13, "codename": "change_patient"}}, {"model": "auth.permission", "pk": 51, "fields": {"name": "Can delete Paciente", "content_type": 13, "codename": "delete_patient"}}, {"model": "auth.permission", "pk": 52, "fields": {"name": "Can view Paciente", "content_type": 13, "codename": "view_patient"}}, {"model": "auth.permission", "pk": 53, "fields": {"name": "Can add Número de Prontuário", "content_type": 14, "codename": "add_patientrecordnumber"}}, {"model": "auth.permission", "pk": 54, "fields": {"name": "Can change Número de Prontuário", "content_type": 14, "codename": "change_patientrecordnumber"}}, {"model": "auth.permission", "pk": 55, "fields": {"name": "Can delete Número de Prontuário", "content_type": 14, "codename": "delete_patientrecordnumber"}}, {"model": "auth.permission", "pk": 56, "fields": {"name": "Can view Número de Prontuário", "content_type": 14, "codename": "view_patientrecordnumber"}}, {"model": "auth.permission", "pk": 57, "fields": {"name": "Can add Tag", "content_type": 15, "codename": "add_tag"}}, {"model": "auth.permission", "pk": 58, "fields": {"name": "Can change Tag", "content_type": 15, "codename": "change_tag"}}, {"model": "auth.permission", "pk": 59, "fields": {"name": "Can delete Tag", "content_type": 15, "codename": "delete_tag"}}, {"model": "auth.permission", "pk": 60, "fields": {"name": "Can view Tag", "content_type": 15, "codename": "view_tag"}}, {"model": "auth.permission", "pk": 61, "fields": {"name": "Can add Internação", "content_type": 16, "codename": "add_patientadmission"}}, {"model": "auth.permission", "pk": 62, "fields": {"name": "Can change Internação", "content_type": 16, "codename": "change_patientadmission"}}, {"model": "auth.permission", "pk": 63, "fields": {"name": "Can delete Internação", "content_type": 16, "codename": "delete_patientadmission"}}, {"model": "auth.permission", "pk": 64, "fields": {"name": "Can view Internação", "content_type": 16, "codename": "view_patientadmission"}}, {"model": "auth.permission", "pk": 65, "fields": {"name": "Can add Evento", "content_type": 17, "codename": "add_event"}}, {"model": "auth.permission", "pk": 66, "fields": {"name": "Can change Evento", "content_type": 17, "codename": "change_event"}}, {"model": "auth.permission", "pk": 67, "fields": {"name": "Can delete Evento", "content_type": 17, "codename": "delete_event"}}, {"model": "auth.permission", "pk": 68, "fields": {"name": "Can view Evento", "content_type": 17, "codename": "view_event"}}, {"model": "auth.permission", "pk": 69, "fields": {"name": "Can edit own events within 24 hours", "content_type": 17, "codename": "edit_own_event_24h"}}, {"model": "auth.permission", "pk": 70, "fields": {"name": "Can delete own events within 24 hours", "content_type": 17, "codename": "delete_own_event_24h"}}, {"model": "auth.permission", "pk": 71, "fields": {"name": "Can add Evento de Tag Adicionada", "content_type": 18, "codename": "add_tagaddedevent"}}, {"model": "auth.permission", "pk": 72, "fields": {"name": "Can change Evento de Tag Adicionada", "content_type": 18, "codename": "change_tagaddedevent"}}, {"model": "auth.permission", "pk": 73, "fields": {"name": "Can delete Evento de Tag Adicionada", "content_type": 18, "codename": "delete_tagaddedevent"}}, {"model": "auth.permission", "pk": 74, "fields": {"name": "Can view Evento de Tag Adicionada", "content_type": 18, "codename": "view_tagaddedevent"}}, {"model": "auth.permission", "pk": 75, "fields": {"name": "Can add Evento de Remoção em Lote de Tags", "content_type": 19, "codename": "add_tagbulkremoveevent"}}, {"model": "auth.permission", "pk": 76, "fields": {"name": "Can change Evento de Remoção em Lote de Tags", "content_type": 19, "codename": "change_tagbulkremoveevent"}}, {"model": "auth.permission", "pk": 77, "fields": {"name": "Can delete Evento de Remoção em Lote de Tags", "content_type": 19, "codename": "delete_tagbulkremoveevent"}}, {"model": "auth.permission", "pk": 78, "fields": {"name": "Can view Evento de Remoção em Lote de Tags", "content_type": 19, "codename": "view_tagbulkremoveevent"}}, {"model": "auth.permission", "pk": 79, "fields": {"name": "Can add Evento de Tag Removida", "content_type": 20, "codename": "add_tagremovedevent"}}, {"model": "auth.permission", "pk": 80, "fields": {"name": "Can change Evento de Tag Removida", "content_type": 20, "codename": "change_tagremovedevent"}}, {"model": "auth.permission", "pk": 81, "fields": {"name": "Can delete Evento de Tag Removida", "content_type": 20, "codename": "delete_tagremovedevent"}}, {"model": "auth.permission", "pk": 82, "fields": {"name": "Can view Evento de Tag Removida", "content_type": 20, "codename": "view_tagremovedevent"}}, {"model": "auth.permission", "pk": 83, "fields": {"name": "Can add Evento de Admissão", "content_type": 21, "codename": "add_admissionevent"}}, {"model": "auth.permission", "pk": 84, "fields": {"name": "Can change Evento de Admissão", "content_type": 21, "codename": "change_admissionevent"}}, {"model": "auth.permission", "pk": 85, "fields": {"name": "Can delete Evento de Admissão", "content_type": 21, "codename": "delete_admissionevent"}}, {"model": "auth.permission", "pk": 86, "fields": {"name": "Can view Evento de Admissão", "content_type": 21, "codename": "view_admissionevent"}}, {"model": "auth.permission", "pk": 87, "fields": {"name": "Can add Evento de Alta", "content_type": 22, "codename": "add_dischargeevent"}}, {"model": "auth.permission", "pk": 88, "fields": {"name": "Can change Evento de Alta", "content_type": 22, "codename": "change_dischargeevent"}}, {"model": "auth.permission", "pk": 89, "fields": {"name": "Can delete Evento de Alta", "content_type": 22, "codename": "delete_dischargeevent"}}, {"model": "auth.permission", "pk": 90, "fields": {"name": "Can view Evento de Alta", "content_type": 22, "codename": "view_dischargeevent"}}, {"model": "auth.permission", "pk": 91, "fields": {"name": "Can add Evento de Alteração de Prontuário", "content_type": 23, "codename": "add_recordnumberchangeevent"}}, {"model": "auth.permission", "pk": 92, "fields": {"name": "Can change Evento de Alteração de Prontuário", "content_type": 23, "codename": "change_recordnumberchangeevent"}}, {"model": "auth.permission", "pk": 93, "fields": {"name": "Can delete Evento de Alteração de Prontuário", "content_type": 23, "codename": "delete_recordnumberchangeevent"}}, {"model": "auth.permission", "pk": 94, "fields": {"name": "Can view Evento de Alteração de Prontuário", "content_type": 23, "codename": "view_recordnumberchangeevent"}}, {"model": "auth.permission", "pk": 95, "fields": {"name": "Can add Evento de Alteração de Status", "content_type": 24, "codename": "add_statuschangeevent"}}, {"model": "auth.permission", "pk": 96, "fields": {"name": "Can change Evento de Alteração de Status", "content_type": 24, "codename": "change_statuschangeevent"}}, {"model": "auth.permission", "pk": 97, "fields": {"name": "Can delete Evento de Alteração de Status", "content_type": 24, "codename": "delete_statuschangeevent"}}, {"model": "auth.permission", "pk": 98, "fields": {"name": "Can view Evento de Alteração de Status", "content_type": 24, "codename": "view_statuschangeevent"}}, {"model": "auth.permission", "pk": 99, "fields": {"name": "Can add Evolução", "content_type": 25, "codename": "add_dailynote"}}, {"model": "auth.permission", "pk": 100, "fields": {"name": "Can change Evolução", "content_type": 25, "codename": "change_dailynote"}}, {"model": "auth.permission", "pk": 101, "fields": {"name": "Can delete Evolução", "content_type": 25, "codename": "delete_dailynote"}}, {"model": "auth.permission", "pk": 102, "fields": {"name": "Can view Evolução", "content_type": 25, "codename": "view_dailynote"}}, {"model": "auth.permission", "pk": 103, "fields": {"name": "Can add Nota Simples", "content_type": 26, "codename": "add_simplenote"}}, {"model": "auth.permission", "pk": 104, "fields": {"name": "Can change Nota Simples", "content_type": 26, "codename": "change_simplenote"}}, {"model": "auth.permission", "pk": 105, "fields": {"name": "Can delete Nota Simples", "content_type": 26, "codename": "delete_simplenote"}}, {"model": "auth.permission", "pk": 106, "fields": {"name": "Can view Nota Simples", "content_type": 26, "codename": "view_simplenote"}}, {"model": "auth.permission", "pk": 107, "fields": {"name": "Can add Foto", "content_type": 27, "codename": "add_photo"}}, {"model": "auth.permission", "pk": 108, "fields": {"name": "Can change Foto", "content_type": 27, "codename": "change_photo"}}, {"model": "auth.permission", "pk": 109, "fields": {"name": "Can delete Foto", "content_type": 27, "codename": "delete_photo"}}, {"model": "auth.permission", "pk": 110, "fields": {"name": "Can view Foto", "content_type": 27, "codename": "view_photo"}}, {"model": "auth.permission", "pk": 111, "fields": {"name": "Can add Série de Fotos", "content_type": 28, "codename": "add_photoseries"}}, {"model": "auth.permission", "pk": 112, "fields": {"name": "Can change Série de Fotos", "content_type": 28, "codename": "change_photoseries"}}, {"model": "auth.permission", "pk": 113, "fields": {"name": "Can delete Série de Fotos", "content_type": 28, "codename": "delete_photoseries"}}, {"model": "auth.permission", "pk": 114, "fields": {"name": "Can view Série de Fotos", "content_type": 28, "codename": "view_photoseries"}}, {"model": "auth.permission", "pk": 115, "fields": {"name": "Can add Vídeo Curto", "content_type": 29, "codename": "add_videoclip"}}, {"model": "auth.permission", "pk": 116, "fields": {"name": "Can change Vídeo Curto", "content_type": 29, "codename": "change_videoclip"}}, {"model": "auth.permission", "pk": 117, "fields": {"name": "Can delete Vídeo Curto", "content_type": 29, "codename": "delete_videoclip"}}, {"model": "auth.permission", "pk": 118, "fields": {"name": "Can view Vídeo Curto", "content_type": 29, "codename": "view_videoclip"}}, {"model": "auth.permission", "pk": 119, "fields": {"name": "Can add Arquivo de Mídia", "content_type": 30, "codename": "add_mediafile"}}, {"model": "auth.permission", "pk": 120, "fields": {"name": "Can change Arquivo de Mídia", "content_type": 30, "codename": "change_mediafile"}}, {"model": "auth.permission", "pk": 121, "fields": {"name": "Can delete Arquivo de Mídia", "content_type": 30, "codename": "delete_mediafile"}}, {"model": "auth.permission", "pk": 122, "fields": {"name": "Can view Arquivo de Mídia", "content_type": 30, "codename": "view_mediafile"}}, {"model": "auth.permission", "pk": 123, "fields": {"name": "Can add photo series file", "content_type": 31, "codename": "add_photoseriesfile"}}, {"model": "auth.permission", "pk": 124, "fields": {"name": "Can change photo series file", "content_type": 31, "codename": "change_photoseriesfile"}}, {"model": "auth.permission", "pk": 125, "fields": {"name": "Can delete photo series file", "content_type": 31, "codename": "delete_photoseriesfile"}}, {"model": "auth.permission", "pk": 126, "fields": {"name": "Can view photo series file", "content_type": 31, "codename": "view_photoseriesfile"}}, {"model": "auth.permission", "pk": 127, "fields": {"name": "Can add Template de Formulário PDF", "content_type": 32, "codename": "add_pdfformtemplate"}}, {"model": "auth.permission", "pk": 128, "fields": {"name": "Can change Template de Formulário PDF", "content_type": 32, "codename": "change_pdfformtemplate"}}, {"model": "auth.permission", "pk": 129, "fields": {"name": "Can delete Template de Formulário PDF", "content_type": 32, "codename": "delete_pdfformtemplate"}}, {"model": "auth.permission", "pk": 130, "fields": {"name": "Can view Template de Formulário PDF", "content_type": 32, "codename": "view_pdfformtemplate"}}, {"model": "auth.permission", "pk": 131, "fields": {"name": "Can add Submissão de Formulário PDF", "content_type": 33, "codename": "add_pdfformsubmission"}}, {"model": "auth.permission", "pk": 132, "fields": {"name": "Can change Submissão de Formulário PDF", "content_type": 33, "codename": "change_pdfformsubmission"}}, {"model": "auth.permission", "pk": 133, "fields": {"name": "Can delete Submissão de Formulário PDF", "content_type": 33, "codename": "delete_pdfformsubmission"}}, {"model": "auth.permission", "pk": 134, "fields": {"name": "Can view Submissão de Formulário PDF", "content_type": 33, "codename": "view_pdfformsubmission"}}, {"model": "auth.permission", "pk": 135, "fields": {"name": "Can add Anamnese e Exame Físico", "content_type": 34, "codename": "add_historyandphysical"}}, {"model": "auth.permission", "pk": 136, "fields": {"name": "Can change Anamnese e Exame Físico", "content_type": 34, "codename": "change_historyandphysical"}}, {"model": "auth.permission", "pk": 137, "fields": {"name": "Can delete Anamnese e Exame Físico", "content_type": 34, "codename": "delete_historyandphysical"}}, {"model": "auth.permission", "pk": 138, "fields": {"name": "Can view Anamnese e Exame Físico", "content_type": 34, "codename": "view_historyandphysical"}}, {"model": "auth.permission", "pk": 139, "fields": {"name": "Can add Conteúdo de Exemplo", "content_type": 35, "codename": "add_samplecontent"}}, {"model": "auth.permission", "pk": 140, "fields": {"name": "Can change Conteúdo de Exemplo", "content_type": 35, "codename": "change_samplecontent"}}, {"model": "auth.permission", "pk": 141, "fields": {"name": "Can delete Conteúdo de Exemplo", "content_type": 35, "codename": "delete_samplecontent"}}, {"model": "auth.permission", "pk": 142, "fields": {"name": "Can view Conteúdo de Exemplo", "content_type": 35, "codename": "view_samplecontent"}}, {"model": "auth.permission", "pk": 143, "fields": {"name": "Can add Template de Prescrição", "content_type": 36, "codename": "add_prescriptiontemplate"}}, {"model": "auth.permission", "pk": 144, "fields": {"name": "Can change Template de Prescrição", "content_type": 36, "codename": "change_prescriptiontemplate"}}, {"model": "auth.permission", "pk": 145, "fields": {"name": "Can delete Template de Prescrição", "content_type": 36, "codename": "delete_prescriptiontemplate"}}, {"model": "auth.permission", "pk": 146, "fields": {"name": "Can view Template de Prescrição", "content_type": 36, "codename": "view_prescriptiontemplate"}}, {"model": "auth.permission", "pk": 147, "fields": {"name": "Can add Item do Template de Prescrição", "content_type": 37, "codename": "add_prescriptiontemplateitem"}}, {"model": "auth.permission", "pk": 148, "fields": {"name": "Can change Item do Template de Prescrição", "content_type": 37, "codename": "change_prescriptiontemplateitem"}}, {"model": "auth.permission", "pk": 149, "fields": {"name": "Can delete Item do Template de Prescrição", "content_type": 37, "codename": "delete_prescriptiontemplateitem"}}, {"model": "auth.permission", "pk": 150, "fields": {"name": "Can view Item do Template de Prescrição", "content_type": 37, "codename": "view_prescriptiontemplateitem"}}, {"model": "auth.permission", "pk": 151, "fields": {"name": "Can add Template de Medicamento", "content_type": 38, "codename": "add_drugtemplate"}}, {"model": "auth.permission", "pk": 152, "fields": {"name": "Can change Template de Medicamento", "content_type": 38, "codename": "change_drugtemplate"}}, {"model": "auth.permission", "pk": 153, "fields": {"name": "Can delete Template de Medicamento", "content_type": 38, "codename": "delete_drugtemplate"}}, {"model": "auth.permission", "pk": 154, "fields": {"name": "Can view Template de Medicamento", "content_type": 38, "codename": "view_drugtemplate"}}, {"model": "auth.permission", "pk": 155, "fields": {"name": "Can add Receita Ambulatorial", "content_type": 39, "codename": "add_outpatientprescription"}}, {"model": "auth.permission", "pk": 156, "fields": {"name": "Can change Receita Ambulatorial", "content_type": 39, "codename": "change_outpatientprescription"}}, {"model": "auth.permission", "pk": 157, "fields": {"name": "Can delete Receita Ambulatorial", "content_type": 39, "codename": "delete_outpatientprescription"}}, {"model": "auth.permission", "pk": 158, "fields": {"name": "Can view Receita Ambulatorial", "content_type": 39, "codename": "view_outpatientprescription"}}, {"model": "auth.permission", "pk": 159, "fields": {"name": "Can add Item da Receita", "content_type": 40, "codename": "add_prescriptionitem"}}, {"model": "auth.permission", "pk": 160, "fields": {"name": "Can change Item da Receita", "content_type": 40, "codename": "change_prescriptionitem"}}, {"model": "auth.permission", "pk": 161, "fields": {"name": "Can delete Item da Receita", "content_type": 40, "codename": "delete_prescriptionitem"}}, {"model": "auth.permission", "pk": 162, "fields": {"name": "Can view Item da Receita", "content_type": 40, "codename": "view_prescriptionitem"}}, {"model": "auth.permission", "pk": 163, "fields": {"name": "Can add email address", "content_type": 41, "codename": "add_emailaddress"}}, {"model": "auth.permission", "pk": 164, "fields": {"name": "Can change email address", "content_type": 41, "codename": "change_emailaddress"}}, {"model": "auth.permission", "pk": 165, "fields": {"name": "Can delete email address", "content_type": 41, "codename": "delete_emailaddress"}}, {"model": "auth.permission", "pk": 166, "fields": {"name": "Can view email address", "content_type": 41, "codename": "view_emailaddress"}}, {"model": "auth.permission", "pk": 167, "fields": {"name": "Can add email confirmation", "content_type": 42, "codename": "add_emailconfirmation"}}, {"model": "auth.permission", "pk": 168, "fields": {"name": "Can change email confirmation", "content_type": 42, "codename": "change_emailconfirmation"}}, {"model": "auth.permission", "pk": 169, "fields": {"name": "Can delete email confirmation", "content_type": 42, "codename": "delete_emailconfirmation"}}, {"model": "auth.permission", "pk": 170, "fields": {"name": "Can view email confirmation", "content_type": 42, "codename": "view_emailconfirmation"}}, {"model": "auth.permission", "pk": 171, "fields": {"name": "Can add social account", "content_type": 43, "codename": "add_socialaccount"}}, {"model": "auth.permission", "pk": 172, "fields": {"name": "Can change social account", "content_type": 43, "codename": "change_socialaccount"}}, {"model": "auth.permission", "pk": 173, "fields": {"name": "Can delete social account", "content_type": 43, "codename": "delete_socialaccount"}}, {"model": "auth.permission", "pk": 174, "fields": {"name": "Can view social account", "content_type": 43, "codename": "view_socialaccount"}}, {"model": "auth.permission", "pk": 175, "fields": {"name": "Can add social application", "content_type": 44, "codename": "add_socialapp"}}, {"model": "auth.permission", "pk": 176, "fields": {"name": "Can change social application", "content_type": 44, "codename": "change_socialapp"}}, {"model": "auth.permission", "pk": 177, "fields": {"name": "Can delete social application", "content_type": 44, "codename": "delete_socialapp"}}, {"model": "auth.permission", "pk": 178, "fields": {"name": "Can view social application", "content_type": 44, "codename": "view_socialapp"}}, {"model": "auth.permission", "pk": 179, "fields": {"name": "Can add social application token", "content_type": 45, "codename": "add_socialtoken"}}, {"model": "auth.permission", "pk": 180, "fields": {"name": "Can change social application token", "content_type": 45, "codename": "change_socialtoken"}}, {"model": "auth.permission", "pk": 181, "fields": {"name": "Can delete social application token", "content_type": 45, "codename": "delete_socialtoken"}}, {"model": "auth.permission", "pk": 182, "fields": {"name": "Can view social application token", "content_type": 45, "codename": "view_socialtoken"}}, {"model": "auth.permission", "pk": 183, "fields": {"name": "Can add temporary upload", "content_type": 46, "codename": "add_temporaryupload"}}, {"model": "auth.permission", "pk": 184, "fields": {"name": "Can change temporary upload", "content_type": 46, "codename": "change_temporaryupload"}}, {"model": "auth.permission", "pk": 185, "fields": {"name": "Can delete temporary upload", "content_type": 46, "codename": "delete_temporaryupload"}}, {"model": "auth.permission", "pk": 186, "fields": {"name": "Can view temporary upload", "content_type": 46, "codename": "view_temporaryupload"}}, {"model": "auth.permission", "pk": 187, "fields": {"name": "Can add stored upload", "content_type": 47, "codename": "add_storedupload"}}, {"model": "auth.permission", "pk": 188, "fields": {"name": "Can change stored upload", "content_type": 47, "codename": "change_storedupload"}}, {"model": "auth.permission", "pk": 189, "fields": {"name": "Can delete stored upload", "content_type": 47, "codename": "delete_storedupload"}}, {"model": "auth.permission", "pk": 190, "fields": {"name": "Can view stored upload", "content_type": 47, "codename": "view_storedupload"}}, {"model": "auth.permission", "pk": 191, "fields": {"name": "Can add temporary upload chunked", "content_type": 48, "codename": "add_temporaryuploadchunked"}}, {"model": "auth.permission", "pk": 192, "fields": {"name": "Can change temporary upload chunked", "content_type": 48, "codename": "change_temporaryuploadchunked"}}, {"model": "auth.permission", "pk": 193, "fields": {"name": "Can delete temporary upload chunked", "content_type": 48, "codename": "delete_temporaryuploadchunked"}}, {"model": "auth.permission", "pk": 194, "fields": {"name": "Can view temporary upload chunked", "content_type": 48, "codename": "view_temporaryuploadchunked"}}]